{
  "211": "多亏老师仔细指导才考过。",
  "212": "因电车晚点重要会议迟到了。",
  "213": "因相信他的话损失大笔钱。",
  "214": "既然约好了就该负责到底。",
  "215": "请仔细调查后得出结论。",
  "216": "多次讨论终于达成一致。",
  "217": "伴随经济发展环境问题也严重了。",
  "218": "随着年龄增长体力下降。",
  "219": "伴随人口增加住房需求也高。",
  "220": "这花形似星星被称为星草。",
  "221": "若下月调到海外怎么办？",
  "222": "不实际做不知真正难度。",
  "223": "只要有时间就能完成这工作。",
  "224": "现在抱怨也改变不了什么。",
  "225": "对上司说那种失礼话会立即被炒。",
  "226": "本人不来这问题解决不了。",
  "227": "这图书馆不问年龄任何人都能用。",
  "228": "不论天气活动按计划举行。",
  "229": "价格且不说先确认品质。",
  "230": "身为社长不能轻易休息。",
  "231": "多次提醒他仍重复同样错误。",
  "232": "他虽在日本住久却日语不太好。",
  "233": "知道有害却戒不了烟。",
  "234": "这计划虽有趣但实现似乎难。",
  "235": "自己什么都不做光抱怨。",
  "236": "这店价格高量却少。",
  "237": "孩子本安静玩突然哭出来。",
  "238": "都市人口增而地方减少。",
  "239": "她温柔但也有严厉一面。",
  "240": "别说旅行搬家准备忙得出不去。",
  "241": "最近常忘东西困扰。",
  "242": "这色是面向儿童的设计。",
  "243": "最近有点累所以早睡。",
  "244": "成功跑完了马拉松。",
  "245": "他坚持到最后做完了。",
  "246": "此请求我们难以接受。",
  "247": "这样放任可能酿成大事故。",
  "248": "既有证据不得不承认事实。",
  "249": "看那电影感动得禁不住哭。",
  "250": "练习这么多明天肯定能赢。",
  "251": "他撒这种谎一定有隐情。",
  "252": "困难时互助才是真正友情。",
  "253": "小时候常在这河捕鱼。",
  "254": "为健康每天该适度运动。",
  "255": "那么温柔的人不可能伤人。",
  "256": "朋友婚礼不得不去。",
  "257": "关于这问题听听专家意见。",
  "258": "日本小孩减少；另一方面老人增加。",
  "259": "下周会议将讨论新企划。",
  "260": "这电影根据真实故事创作。",
  "261": "论做菜的速度无人能及她。",
  "262": "以留学为契机对外国文化感兴趣。",
  "263": "通过互联网能获取世界信息。",
  "264": "这教材面向初学者制作。",
  "265": "成功与否取决于本人的努力。",
  "266": "做菜途中电话响了。",
  "267": "趁年轻应多积累经验。",
  "268": "听这曲就想起学生时代。",
  "269": "回家时请确认有无遗落物。",
  "270": "长时间讨论的结果终于得出结论。"
}